cwms/__init__.py
cwms/api.py
cwms/catalog/blobs.py
cwms/catalog/catalog.py
cwms/catalog/clobs.py
cwms/cwms_types.py
cwms/forecast/forecast_instance.py
cwms/forecast/forecast_spec.py
cwms/levels/location_levels.py
cwms/levels/specified_levels.py
cwms/locations/gate_changes.py
cwms/locations/location_groups.py
cwms/locations/physical_locations.py
cwms/measurements/measurements.py
cwms/outlets/outlets.py
cwms/outlets/virtual_outlets.py
cwms/projects/project_lock_rights.py
cwms/projects/project_locks.py
cwms/projects/projects.py
cwms/projects/water_supply/accounting.py
cwms/ratings/ratings.py
cwms/ratings/ratings_spec.py
cwms/ratings/ratings_template.py
cwms/standard_text/standard_text.py
cwms/timeseries/timeseries.py
cwms/timeseries/timeseries_bin.py
cwms/timeseries/timeseries_group.py
cwms/timeseries/timeseries_identifier.py
cwms/timeseries/timeseries_profile.py
cwms/timeseries/timeseries_profile_instance.py
cwms/timeseries/timeseries_profile_parser.py
cwms/timeseries/timeseries_txt.py
cwms/turbines/turbines.py
cwms/utils/__init__.py
cwms/utils/checks.py
cwms_python-1.0.1.dist-info/METADATA
cwms_python-1.0.1.dist-info/WHEEL
cwms_python-1.0.1.dist-info/licenses/LICENSE
cwms_python-1.0.1.dist-info/RECORD
