Metadata-Version: 2.4
Name: cwms-python
Version: 1.0.1
Summary: Corps water management systems (CWMS) REST API for Data Retrieval of USACE water data
License: LICENSE
License-File: LICENSE
Keywords: USACE,water data,CWMS
Author: Eric Novotny
Author-email: eric.v.novotny@usace.army.mil
Requires-Python: >=3.9,<4.0
Classifier: License :: Other/Proprietary License
Classifier: Programming Language :: Python :: 3
Classifier: Programming Language :: Python :: 3.9
Classifier: Programming Language :: Python :: 3.10
Classifier: Programming Language :: Python :: 3.11
Classifier: Programming Language :: Python :: 3.12
Classifier: Programming Language :: Python :: 3.13
Classifier: Programming Language :: Python :: 3.14
Requires-Dist: pandas (>=2.1.3,<3.0.0)
Requires-Dist: requests (>=2.31.0,<3.0.0)
Requires-Dist: requests-toolbelt (>=1.0.0,<2.0.0)
Project-URL: Repository, https://github.com/HydrologicEngineeringCenter/cwms-python
